LICENSE
MANIFEST.in
README.rst
requirements.txt
setup.py
django_randsense.egg-info/PKG-INFO
django_randsense.egg-info/SOURCES.txt
django_randsense.egg-info/dependency_links.txt
django_randsense.egg-info/requires.txt
django_randsense.egg-info/top_level.txt
randsense/__init__.py
randsense/admin.py
randsense/grammar.txt
randsense/inflections.py
randsense/lexicon.xml
randsense/models.py
randsense/sentences.py
randsense/serializers.py
randsense/settings.py
randsense/tests.py
randsense/urls.py
randsense/views.py
randsense/wsgi.py
randsense/management/__init__.py
randsense/management/commands/__init__.py
randsense/management/commands/lexicon_dump.py
randsense/management/commands/normalize_numbers.py
randsense/management/commands/populate_words.py
randsense/migrations/0001_initial.py
randsense/migrations/__init__.py